{
  "locked_profile": {
    "dataset": "CWRU",
    "preprocess": "STFT",
    "ways": 5,
    "train_domains": "0,1,2",
    "test_domain": 3,
    "runtime_backend": "onnxruntime",
    "enable_compression": true,
    "prune_ratio": 0.4,
    "fault_labels": ""
  },
  "table0_preprocess_model_matrix": [
    {
      "preprocess": "FFT",
      "model": "CNN",
      "shots": 5,
      "accuracy": 0.9634831460674157,
      "accuracy_percent": 96.35,
      "latency_ms": 0.9705,
      "metric_protocol": "deployment_baseline",
      "experiment_title": "CNN_CWRU_FFT_5w5s5q_source123_target0_labels0123456789"
    },
    {
      "preprocess": "FFT",
      "model": "CNN",
      "shots": 10,
      "accuracy": 0.875,
      "accuracy_percent": 87.5,
      "latency_ms": 1.2666,
      "metric_protocol": "deployment_baseline",
      "experiment_title": "CNN_CWRU_FFT_5w10s10q_source123_target0_labels0123456789"
    },
    {
      "preprocess": "FFT",
      "model": "CNN",
      "shots": 15,
      "accuracy": 0.9283707865168539,
      "accuracy_percent": 92.84,
      "latency_ms": 1.1872,
      "metric_protocol": "deployment_baseline",
      "experiment_title": "CNN_CWRU_FFT_5w15s15q_source123_target0_labels0123456789"
    },
    {
      "preprocess": "FFT",
      "model": "MAML",
      "shots": 5,
      "accuracy": 0.9747191011235955,
      "accuracy_percent": 97.47,
      "latency_ms": 1.2303,
      "metric_protocol": "deployment_baseline",
      "experiment_title": "MAML_CWRU_FFT_5w5s_source123_target0_labels0123456789"
    },
    {
      "preprocess": "FFT",
      "model": "MAML",
      "shots": 10,
      "accuracy": 0.9452247191011236,
      "accuracy_percent": 94.52,
      "latency_ms": 1.1513,
      "metric_protocol": "deployment_baseline",
      "experiment_title": "MAML_CWRU_FFT_5w10s_source123_target0_labels0123456789"
    },
    {
      "preprocess": "FFT",
      "model": "MAML",
      "shots": 15,
      "accuracy": 1.0,
      "accuracy_percent": 100.0,
      "latency_ms": 1.1018,
      "metric_protocol": "deployment_baseline",
      "experiment_title": "MAML_CWRU_FFT_5w15s_source123_target0_labels0123456789"
    },
    {
      "preprocess": "FFT",
      "model": "ProtoNet",
      "shots": 5,
      "accuracy": 0.9985955056179775,
      "accuracy_percent": 99.86,
      "latency_ms": 1.2587,
      "metric_protocol": "deployment_baseline",
      "experiment_title": "ProtoNet_CWRU_FFT_5w5s5q_source123_target0_labels0123456789"
    },
    {
      "preprocess": "FFT",
      "model": "ProtoNet",
      "shots": 10,
      "accuracy": 0.9985955056179775,
      "accuracy_percent": 99.86,
      "latency_ms": 1.1942,
      "metric_protocol": "deployment_baseline",
      "experiment_title": "ProtoNet_CWRU_FFT_5w10s10q_source123_target0_labels0123456789"
    },
    {
      "preprocess": "FFT",
      "model": "ProtoNet",
      "shots": 15,
      "accuracy": 1.0,
      "accuracy_percent": 100.0,
      "latency_ms": 1.2404,
      "metric_protocol": "deployment_baseline",
      "experiment_title": "ProtoNet_CWRU_FFT_5w15s15q_source123_target0_labels0123456789"
    },
    {
      "preprocess": "STFT",
      "model": "CNN",
      "shots": 5,
      "accuracy": 0.8160112359550562,
      "accuracy_percent": 81.6,
      "latency_ms": 2.718,
      "metric_protocol": "deployment_baseline",
      "experiment_title": "CNN_CWRU_STFT_5w5s5q_source123_target0_labels0123456789"
    },
    {
      "preprocess": "STFT",
      "model": "CNN",
      "shots": 10,
      "accuracy": 0.9367977528089888,
      "accuracy_percent": 93.68,
      "latency_ms": 2.8804,
      "metric_protocol": "deployment_baseline",
      "experiment_title": "CNN_CWRU_STFT_5w10s10q_source123_target0_labels0123456789"
    },
    {
      "preprocess": "STFT",
      "model": "CNN",
      "shots": 15,
      "accuracy": 0.9353932584269663,
      "accuracy_percent": 93.54,
      "latency_ms": 2.7157,
      "metric_protocol": "deployment_baseline",
      "experiment_title": "CNN_CWRU_STFT_5w15s15q_source123_target0_labels0123456789"
    },
    {
      "preprocess": "STFT",
      "model": "MAML",
      "shots": 5,
      "accuracy": 0.9676966292134831,
      "accuracy_percent": 96.77,
      "latency_ms": 2.889,
      "metric_protocol": "deployment_baseline",
      "experiment_title": "MAML_CWRU_STFT_5w5s_source123_target0_labels0123456789"
    },
    {
      "preprocess": "STFT",
      "model": "MAML",
      "shots": 10,
      "accuracy": 0.973314606741573,
      "accuracy_percent": 97.33,
      "latency_ms": 2.6667,
      "metric_protocol": "deployment_baseline",
      "experiment_title": "MAML_CWRU_STFT_5w10s_source123_target0_labels0123456789"
    },
    {
      "preprocess": "STFT",
      "model": "MAML",
      "shots": 15,
      "accuracy": 0.9634831460674157,
      "accuracy_percent": 96.35,
      "latency_ms": 2.8577,
      "metric_protocol": "deployment_baseline",
      "experiment_title": "MAML_CWRU_STFT_5w15s_source123_target0_labels0123456789"
    },
    {
      "preprocess": "STFT",
      "model": "ProtoNet",
      "shots": 5,
      "accuracy": 0.9817415730337079,
      "accuracy_percent": 98.17,
      "latency_ms": 2.8,
      "metric_protocol": "deployment_baseline",
      "experiment_title": "ProtoNet_CWRU_STFT_5w5s5q_source123_target0_labels0123456789"
    },
    {
      "preprocess": "STFT",
      "model": "ProtoNet",
      "shots": 10,
      "accuracy": 0.973314606741573,
      "accuracy_percent": 97.33,
      "latency_ms": 2.7818,
      "metric_protocol": "deployment_baseline",
      "experiment_title": "ProtoNet_CWRU_STFT_5w10s10q_source123_target0_labels0123456789"
    },
    {
      "preprocess": "STFT",
      "model": "ProtoNet",
      "shots": 15,
      "accuracy": 0.9873595505617978,
      "accuracy_percent": 98.74,
      "latency_ms": 2.6528,
      "metric_protocol": "deployment_baseline",
      "experiment_title": "ProtoNet_CWRU_STFT_5w15s15q_source123_target0_labels0123456789"
    },
    {
      "preprocess": "WT",
      "model": "CNN",
      "shots": 5,
      "accuracy": 0.8609550561797753,
      "accuracy_percent": 86.1,
      "latency_ms": 2.7304,
      "metric_protocol": "deployment_baseline",
      "experiment_title": "CNN_CWRU_WT_5w5s5q_source123_target0_labels0123456789"
    },
    {
      "preprocess": "WT",
      "model": "CNN",
      "shots": 10,
      "accuracy": 0.922752808988764,
      "accuracy_percent": 92.28,
      "latency_ms": 2.7657,
      "metric_protocol": "deployment_baseline",
      "experiment_title": "CNN_CWRU_WT_5w10s10q_source123_target0_labels0123456789"
    },
    {
      "preprocess": "WT",
      "model": "CNN",
      "shots": 15,
      "accuracy": 0.9157303370786517,
      "accuracy_percent": 91.57,
      "latency_ms": 2.745,
      "metric_protocol": "deployment_baseline",
      "experiment_title": "CNN_CWRU_WT_5w15s15q_source123_target0_labels0123456789"
    },
    {
      "preprocess": "WT",
      "model": "MAML",
      "shots": 5,
      "accuracy": 0.9339887640449438,
      "accuracy_percent": 93.4,
      "latency_ms": 2.873,
      "metric_protocol": "deployment_baseline",
      "experiment_title": "MAML_CWRU_WT_5w5s_source123_target0_labels0123456789"
    },
    {
      "preprocess": "WT",
      "model": "MAML",
      "shots": 10,
      "accuracy": 0.9789325842696629,
      "accuracy_percent": 97.89,
      "latency_ms": 3.0974,
      "metric_protocol": "deployment_baseline",
      "experiment_title": "MAML_CWRU_WT_5w10s_source123_target0_labels0123456789"
    },
    {
      "preprocess": "WT",
      "model": "MAML",
      "shots": 15,
      "accuracy": 0.9508426966292135,
      "accuracy_percent": 95.08,
      "latency_ms": 2.7979,
      "metric_protocol": "deployment_baseline",
      "experiment_title": "MAML_CWRU_WT_5w15s_source123_target0_labels0123456789"
    },
    {
      "preprocess": "WT",
      "model": "ProtoNet",
      "shots": 5,
      "accuracy": 0.9901685393258427,
      "accuracy_percent": 99.02,
      "latency_ms": 2.8875,
      "metric_protocol": "deployment_baseline",
      "experiment_title": "ProtoNet_CWRU_WT_5w5s5q_source123_target0_labels0123456789"
    },
    {
      "preprocess": "WT",
      "model": "ProtoNet",
      "shots": 10,
      "accuracy": 0.9929775280898876,
      "accuracy_percent": 99.3,
      "latency_ms": 2.6654,
      "metric_protocol": "deployment_baseline",
      "experiment_title": "ProtoNet_CWRU_WT_5w10s10q_source123_target0_labels0123456789"
    },
    {
      "preprocess": "WT",
      "model": "ProtoNet",
      "shots": 15,
      "accuracy": 0.9943820224719101,
      "accuracy_percent": 99.44,
      "latency_ms": 2.868,
      "metric_protocol": "deployment_baseline",
      "experiment_title": "ProtoNet_CWRU_WT_5w15s15q_source123_target0_labels0123456789"
    }
  ],
  "table1_model_performance": [],
  "table2_few_shot": [],
  "table3_compression": [],
  "table4_system_performance": []
}